toms_dist_sampler/DistributionSampler.py
toms_dist_sampler/__init__.py
toms_dist_sampler/distribution_sampler.py
toms_dist_sampler-0.0.2.dist-info/LICENSE
toms_dist_sampler-0.0.2.dist-info/METADATA
toms_dist_sampler-0.0.2.dist-info/WHEEL
toms_dist_sampler-0.0.2.dist-info/top_level.txt
toms_dist_sampler-0.0.2.dist-info/RECORD
