Metadata-Version: 2.1
Name: toms-dist-sampler
Version: 0.0.2
Summary: A distribution sampler for Normal, Poisson and Binomial distributions.
Home-page: https://github.com/Tommo565/distribution-sampler
Author: Flying Circus
Author-email: ewingt1979@gmail.com
License: MIT
Platform: UNKNOWN
Classifier: Development Status :: 3 - Alpha
Classifier: Programming Language :: Python :: 3.7
Classifier: Operating System :: OS Independent
